pyudisk/__init__.py
pyudisk/config.py
pyudisk/disk_data.py
pyudisk/logger.py
pyudisk/main.py
pyudisk/metrics.py
pyudisk/notification.py
pyudisk/parsers.py
pyudisk/util.py
pyudisk/models/__init__.py
pyudisk/models/smartctl.py
pyudisk/models/udisk.py
pyudisk/templates/Darwin.html
pyudisk/templates/Linux.html
PyUdisk-2.0.1.dist-info/LICENSE
PyUdisk-2.0.1.dist-info/METADATA
PyUdisk-2.0.1.dist-info/WHEEL
PyUdisk-2.0.1.dist-info/entry_points.txt
PyUdisk-2.0.1.dist-info/top_level.txt
PyUdisk-2.0.1.dist-info/RECORD
