Metadata-Version: 2.1
Name: PyUdisk
Version: 2.0.1
Summary: Extensive disk monitor for Linux OS
Author-email: Vignesh Rao <svignesh1793@gmail.com>
License: MIT License
Project-URL: Homepage, https://github.com/thevickypedia/PyUdisk
Project-URL: Source, https://github.com/thevickypedia/PyUdisk
Keywords: disk-monitor,PyUdisk
Classifier: License :: OSI Approved :: MIT License
Classifier: Programming Language :: Python :: 3
Classifier: Development Status :: 5 - Production/Stable
Classifier: Operating System :: POSIX :: Linux
Classifier: Topic :: System :: Monitoring
Requires-Python: >=3.10
License-File: LICENSE
Requires-Dist: click==8.1.*
Requires-Dist: psutil==6.0.*
Requires-Dist: PyArchitecture>=0.3.0
Requires-Dist: pydantic==2.*
Requires-Dist: pydantic-settings==2.*
Provides-Extra: dev
Requires-Dist: pre-commit; extra == "dev"
Provides-Extra: standard
Requires-Dist: Jinja2==3.1.*; extra == "standard"
Requires-Dist: requests==2.*; extra == "standard"
Requires-Dist: gmail-connector; extra == "standard"
